<ns0:systemMetadata xmlns:ns0="http://ns.dataone.org/service/types/v1">
    <serialVersion>1</serialVersion>
    <identifier>knb-lter-fce.1111.4</identifier>
    <formatId>eml://ecoinformatics.org/eml-2.1.0</formatId>
    <size>62340</size>
    <checksum algorithm="MD5">b911ea3a126ae5e83cdbbe1ef2dc8aba</checksum>
    <submitter>uid=FCE,o=LTER,dc=ecoinformatics,dc=org</submitter>
    <rightsHolder>uid=FCE,o=LTER,dc=ecoinformatics,dc=org</rightsHolder>
    <accessPolicy>
        <allow>
            <subject>public</subject>
            <permission>read</permission>
        </allow>
        <allow>
            <subject>uid=FCE,o=lter,dc=ecoinformatics,dc=org</subject>
            <permission>read</permission>
        </allow>
    </accessPolicy>
    <replicationPolicy replicationAllowed="false" />
    <obsoletes>knb-lter-fce.1111.3</obsoletes>
    <archived>false</archived>
    <dateUploaded>2013-05-06T23:00:00.000+00:00</dateUploaded>
    <dateSysMetadataModified>2014-07-02T14:21:24.213+00:00</dateSysMetadataModified>
    <originMemberNode>urn:node:LTER</originMemberNode>
    <authoritativeMemberNode>urn:node:LTER</authoritativeMemberNode>
    <replica>
        <replicaMemberNode>urn:node:LTER</replicaMemberNode>
        <replicationStatus>completed</replicationStatus>
        <replicaVerified>2014-07-02T14:21:22.585+00:00</replicaVerified>
    </replica>
    <replica>
        <replicaMemberNode>urn:node:CN</replicaMemberNode>
        <replicationStatus>completed</replicationStatus>
        <replicaVerified>2014-07-02T14:21:22.658+00:00</replicaVerified>
    </replica>
</ns0:systemMetadata>