<ns0:eml xmlns:ns0="eml://ecoinformatics.org/eml-2.1.0" xmlns:xsi="http://www.w3.org/2001/XMLSchema-instance" packageId="knb-lter-bnz.90.18" scope="system" system="knb" xsi:schemaLocation="eml://ecoinformatics.org/eml-2.1.0&#10;				http://nis.lternet.edu/schemas/EML/eml-2.1.0/eml.xsd">
<access authSystem="knb" order="allowFirst" scope="document">
<allow>
<principal>uid=BNZ,o=lter,dc=ecoinformatics,dc=org</principal>
<permission>all</permission>
</allow>
<allow>
<principal>public</principal>
<permission>read</permission>
</allow>
</access>
<dataset>
<shortName>knb-lter-bnz.90.18</shortName>
<title>Estimates of White Spruce density at two elevations from 1600-present</title>
<creator>
<individualName>
<givenName>Andrea</givenName>
<givenName>H.</givenName>
<surName>Lloyd</surName>
</individualName>
<positionName>Senior Investigator</positionName>
<address>
<deliveryPoint>Department of Biology Middlebury College Old Chaple 207</deliveryPoint>
<city>Middlebury</city>
<administrativeArea>VT</administrativeArea>
<postalCode>05753</postalCode>
<country>United States</country>
</address>
<phone phonetype="voice">(802) 443-3165</phone>
<phone phonetype="fax">(802) 443-2072</phone>
<electronicMailAddress>lloyd@middlebury.edu</electronicMailAddress>
<onlineUrl>	</onlineUrl>
</creator>
<creator>
<individualName>
<givenName>Christopher</givenName>
<givenName>L.</givenName>
<surName>Fastie</surName>
</individualName>
<positionName>Affiliate Scientist</positionName>
<address>
<deliveryPoint>Department of Biology Middlebury College</deliveryPoint>
<city>Middlebury</city>
<administrativeArea>VT</administrativeArea>
<postalCode>05753</postalCode>
<country>United States</country>
</address>
<phone phonetype="voice">(802) 352-9028</phone>

<electronicMailAddress>cfastie@middlebury.edu</electronicMailAddress>

</creator>
<creator>
<organizationName>Bonanza Creek LTER</organizationName>
<address>
<deliveryPoint>Boreal Ecology Cooperative Research Unit </deliveryPoint>
<deliveryPoint>University of Alaska Fairbanks</deliveryPoint>
<deliveryPoint>P.O. Box 756780 </deliveryPoint>
<city>Fairbanks</city>
<administrativeArea>AK</administrativeArea>
<postalCode>99775</postalCode>
<country>USA</country>
</address>
<phone phonetype="voice">907-474-6364</phone>
<phone phonetype="fax">907-474-6251</phone>
<electronicMailAddress>uaf-bnz-im-team@alaska.edu</electronicMailAddress>
<onlineUrl>http://www.lter.uaf.edu</onlineUrl>
</creator>
<metadataProvider>
<organizationName>Bonanza Creek LTER</organizationName>
<positionName>Data Manager</positionName>
<address>
<deliveryPoint>Boreal Ecology Cooperative Research Unit </deliveryPoint>
<deliveryPoint>University of Alaska Fairbanks</deliveryPoint>
<deliveryPoint>P.O. Box 756780 </deliveryPoint>
<city>Fairbanks</city>
<administrativeArea>AK</administrativeArea>
<postalCode>99775</postalCode>
<country>USA</country>
</address>
<phone phonetype="voice">907-474-6364</phone>
<phone phonetype="fax">907-474-6251</phone>
<electronicMailAddress>uaf-bnz-im-team@alaska.edu</electronicMailAddress>
<onlineUrl>http://www.lter.uaf.edu</onlineUrl>
</metadataProvider>

<pubDate>2002-09-28</pubDate>
<abstract>
<para>Paleoecological investigations of ecosystem responses to past climate change can provide insight into plausible scenarios of response to future change and can elucidate factors that may influence the overall predictability of such responses. There is particular interest in the rate at which subarctic Picea populations respond to climate change, as the rate of conversion from tundra to forest may affect the rate of future climate warming. We investigated recent changes in the structure and distribution of treeline white spruce forests in the White Mountains and the Alaska Range. Treeline advance was ubiquitous, but asynchronous in time, occurring significantly earlier in the White Mountains in interior Alaska than in the Alaska Range. The mean lag between initiation of recruitment and forest development was estimated at approximately 200 years, similar to what modeling studies have found. Although continued advance of Picea is the most likely scenario of future change, the recent history of treeline advance suggests that nonlinear responses to warming may be likely due to nonlinear growth responses of individual trees to temperature, limitation of Picea establishment in highly permafrost-affected sites, and decreasing seed availability as the advancing front moves farther from dense seed sources. All of these factors may cause Picea populations to respond nonlinearly to future warming, and these potential nonlinearities caution against uncritical extrapolation from recent trends.</para>
</abstract>
<keywordSet>
<keyword>paleoecological</keyword>
<keyword>climate</keyword>
<keyword>picea</keyword>
<keyword>spruce</keyword>
<keyword>tundra</keyword>
<keyword>forests</keyword>
<keyword>warming</keyword>
<keyword>white mountains</keyword>
<keyword>Alaska Range</keyword>
<keyword>treeline</keyword>
<keyword>treeline</keyword>
<keywordThesaurus>Stand Structure</keywordThesaurus>
</keywordSet>
<intellectualRights>
<section>
<title>Access to Data</title>
<para>While metadata will be freely available to those requesting it, the data manager will assure that any restrictions on access to data sets in the database will be enforced. Data will not be released without proper permission first being obtained from the investigator who generated the data. </para>
</section>
<section>
<title>Use of data</title>
<para> Researchers should receive adequate acknowledgment for the use of their data by others and should be provided with copies of publications using their data. Users of data from the data base must be aware that data is not to be sold or redistributed.</para>
</section>
<section>
<title>Citing Bonanza Creek LTER Datasets</title>
<para>It is considered a matter of professional ethics to acknowledge the work of other scientists. Thus, the Data User will properly cite the Data Set in any publications or in the metadata of any derived data products that were produced using the Data Set. </para>
</section>
</intellectualRights>
<distribution id="distributionReference">
<online>
<url function="information">http://www.lter.uaf.edu/data_detail.cfm?datafile_pkey=90</url>
</online>
</distribution>
<coverage>
<geographicCoverage id="geoReference">
<geographicDescription>Site information unavailable</geographicDescription>
<boundingCoordinates>
<westBoundingCoordinate>-147.3333333</westBoundingCoordinate>
<eastBoundingCoordinate>-144.05</eastBoundingCoordinate>
<northBoundingCoordinate>65.5</northBoundingCoordinate>
<southBoundingCoordinate>63.25</southBoundingCoordinate>
</boundingCoordinates>
</geographicCoverage>
<temporalCoverage>
<rangeOfDates>
<beginDate>
<calendarDate>2002-06-01</calendarDate>
</beginDate>
<endDate>
<calendarDate>2002-09-28</calendarDate>
</endDate>
</rangeOfDates>
</temporalCoverage>
</coverage>
<maintenance>
<description>
<section>
<title>Status</title>
<para>Completed</para>
</section>
</description>
</maintenance>
<contact>
<organizationName>Bonanza Creek LTER</organizationName>
<positionName>Data Manager</positionName>
<address>
<deliveryPoint>Boreal Ecology Cooperative Research Unit </deliveryPoint>
<deliveryPoint>University of Alaska Fairbanks</deliveryPoint>
<deliveryPoint>P.O. Box 756780 </deliveryPoint>
<city>Fairbanks</city>
<administrativeArea>AK</administrativeArea>
<postalCode>99775</postalCode>
<country>USA</country>
</address>
<phone phonetype="voice">907-474-6364</phone>
<phone phonetype="fax">907-474-6251</phone>
<electronicMailAddress>uaf-bnz-im-team@alaska.edu</electronicMailAddress>
<onlineUrl>http://www.lter.uaf.edu</onlineUrl>
</contact>
<publisher>
<organizationName>Bonanza Creek LTER</organizationName>
<address>
<deliveryPoint>Boreal Ecology Cooperative Research Unit </deliveryPoint>
<deliveryPoint>University of Alaska Fairbanks</deliveryPoint>
<deliveryPoint>P.O. Box 756780 </deliveryPoint>
<city>Fairbanks</city>
<administrativeArea>AK</administrativeArea>
<postalCode>99775</postalCode>
<country>USA</country>
</address>
<phone phonetype="voice">907-474-6364</phone>
<phone phonetype="fax">907-474-6251</phone>
</publisher>
<pubPlace>Bonanza Creek LTER</pubPlace>

<dataTable>
<entityName>157_1569_tree_density_1600_2000.csv</entityName>
<entityDescription>tree density 1600-2000.csv,Contains the estimated density of live white spruce (in units of trees/ha) at each of two elevations at each study site from 1600-present.</entityDescription>
<physical>
<objectName>157_1569_tree_density_1600_2000.csv</objectName>
<dataFormat>
<textFormat>
<numHeaderLines>1</numHeaderLines>
<recordDelimiter>\n</recordDelimiter>
<physicalLineDelimiter>\n</physicalLineDelimiter>
<attributeOrientation>column</attributeOrientation>
<simpleDelimited>
<fieldDelimiter>,</fieldDelimiter>
</simpleDelimited>
</textFormat>
</dataFormat>
<distribution>
<online>
<url function="download">http://www.lter.uaf.edu/ascii/files/157_1569_tree_density_1600_2000.csv</url>
</online>
</distribution>
</physical>
<attributeList>
<attribute>
<attributeName>Year</attributeName>
<attributeLabel>Year</attributeLabel>
<attributeDefinition>Year of treeline</attributeDefinition>
<storageType>integer</storageType>
<measurementScale>
<ratio>
<unit>
<standardUnit>nominalYear</standardUnit>
</unit>
<numericDomain>
<numberType>real</numberType>

</numericDomain>
</ratio>
</measurementScale>

</attribute>
<attribute>
<attributeName>Monahan_treelin</attributeName>
<attributeLabel>Monahan_treelin</attributeLabel>
<attributeDefinition>Density of White Spruce at treeline in Monahan (located in the Alaska Range)</attributeDefinition>
<storageType>float</storageType>
<measurementScale>
<ratio>
<unit>
<standardUnit>dimensionless</standardUnit>
</unit>
<numericDomain>
<numberType>real</numberType>

</numericDomain>
</ratio>
</measurementScale>

</attribute>
<attribute>
<attributeName>Monahan_above</attributeName>
<attributeLabel>Monahan_above</attributeLabel>
<attributeDefinition>Density of White Spruce above treeline in Monahan (loacted in the Alaska Range)</attributeDefinition>
<storageType>float</storageType>
<measurementScale>
<ratio>
<unit>
<standardUnit>dimensionless</standardUnit>
</unit>
<numericDomain>
<numberType>real</numberType>

</numericDomain>
</ratio>
</measurementScale>

</attribute>
<attribute>
<attributeName>Wrangell_treeline</attributeName>
<attributeLabel>Wrangell_treeline</attributeLabel>
<attributeDefinition>Density of White Spruce at tree line in Wrangell (located in the Alaska Range)</attributeDefinition>
<storageType>float </storageType>
<measurementScale>
<ratio>
<unit>
<standardUnit>dimensionless</standardUnit>
</unit>
<numericDomain>
<numberType>real</numberType>

</numericDomain>
</ratio>
</measurementScale>

</attribute>
<attribute>
<attributeName>Wrangell_above</attributeName>
<attributeLabel>Wrangell_above</attributeLabel>
<attributeDefinition>Density of White Spruce above tree line in Wrangell (located in the Alaska Range)</attributeDefinition>
<storageType>float</storageType>
<measurementScale>
<ratio>
<unit>
<standardUnit>dimensionless</standardUnit>
</unit>
<numericDomain>
<numberType>real</numberType>

</numericDomain>
</ratio>
</measurementScale>

</attribute>
<attribute>
<attributeName>Canyon_treeline</attributeName>
<attributeLabel>Canyon_treeline</attributeLabel>
<attributeDefinition>Density of White Spruce at treeline in Canyon (located in the Alaska Range)</attributeDefinition>
<storageType>integer</storageType>
<measurementScale>
<ratio>
<unit>
<standardUnit>dimensionless</standardUnit>
</unit>
<numericDomain>
<numberType>real</numberType>

</numericDomain>
</ratio>
</measurementScale>

</attribute>
<attribute>
<attributeName>Canyon_above</attributeName>
<attributeLabel>Canyon_above</attributeLabel>
<attributeDefinition>Density of White Spruce above tree line in Canyon (located in the Alaska Range)</attributeDefinition>
<storageType>integer</storageType>
<measurementScale>
<ratio>
<unit>
<standardUnit>dimensionless</standardUnit>
</unit>
<numericDomain>
<numberType>real</numberType>

</numericDomain>
</ratio>
</measurementScale>

</attribute>
<attribute>
<attributeName>Usibelli_treeline</attributeName>
<attributeLabel>Usibelli_treeline</attributeLabel>
<attributeDefinition>Density of White Spruce at tree line in Usibelli (located in the Alaska Range)</attributeDefinition>
<storageType>float</storageType>
<measurementScale>
<ratio>
<unit>
<standardUnit>dimensionless</standardUnit>
</unit>
<numericDomain>
<numberType>real</numberType>

</numericDomain>
</ratio>
</measurementScale>

</attribute>
<attribute>
<attributeName>Usibelli_above</attributeName>
<attributeLabel>Usibelli_above</attributeLabel>
<attributeDefinition>Density of White Spruce above tree line in Usibelli (located in the Alaska Range)</attributeDefinition>
<storageType>float</storageType>
<measurementScale>
<ratio>
<unit>
<standardUnit>dimensionless</standardUnit>
</unit>
<numericDomain>
<numberType>real</numberType>

</numericDomain>
</ratio>
</measurementScale>

</attribute>
<attribute>
<attributeName>NomeCreek_treeline</attributeName>
<attributeLabel>NomeCreek_treeline</attributeLabel>
<attributeDefinition>Density of White Spruce at tree line in Nome Creek (located in White Mountains)</attributeDefinition>
<storageType>float </storageType>
<measurementScale>
<ratio>
<unit>
<standardUnit>dimensionless</standardUnit>
</unit>
<numericDomain>
<numberType>real</numberType>

</numericDomain>
</ratio>
</measurementScale>

</attribute>
<attribute>
<attributeName>NomeCreek_above</attributeName>
<attributeLabel>NomeCreek_above</attributeLabel>
<attributeDefinition>Density of White Spruce above tree line in Nome Creek (located in White Mountains)</attributeDefinition>
<storageType>float</storageType>
<measurementScale>
<ratio>
<unit>
<standardUnit>dimensionless</standardUnit>
</unit>
<numericDomain>
<numberType>real</numberType>

</numericDomain>
</ratio>
</measurementScale>

</attribute>
<attribute>
<attributeName>Twelvemile_treeline</attributeName>
<attributeLabel>Twelvemile_treeline</attributeLabel>
<attributeDefinition>Density of White Spruce at tree line in Twelve Mile (located in White Mountains)</attributeDefinition>
<storageType>integer</storageType>
<measurementScale>
<ratio>
<unit>
<standardUnit>dimensionless</standardUnit>
</unit>
<numericDomain>
<numberType>real</numberType>

</numericDomain>
</ratio>
</measurementScale>

</attribute>
<attribute>
<attributeName>Twelvemile_above</attributeName>
<attributeLabel>Twelvemile_above</attributeLabel>
<attributeDefinition>Density of White Spruce above tree line in Twelve Mile (located in White Mountains)</attributeDefinition>
<storageType>float</storageType>
<measurementScale>
<ratio>
<unit>
<standardUnit>dimensionless</standardUnit>
</unit>
<numericDomain>
<numberType>real</numberType>

</numericDomain>
</ratio>
</measurementScale>

</attribute>
<attribute>
<attributeName>EagleSummit_treeline</attributeName>
<attributeLabel>EagleSummit_treeline</attributeLabel>
<attributeDefinition>Density of White Spruce at tree line in Eagle Summit (located in White Mountains)</attributeDefinition>
<storageType>integer</storageType>
<measurementScale>
<ratio>
<unit>
<standardUnit>dimensionless</standardUnit>
</unit>
<numericDomain>
<numberType>real</numberType>

</numericDomain>
</ratio>
</measurementScale>

</attribute>
<attribute>
<attributeName>EagleSummit_above</attributeName>
<attributeLabel>EagleSummit_above</attributeLabel>
<attributeDefinition>Density of White Spruce above tree line in Eagle Summit (located in White Mountains)</attributeDefinition>
<storageType>integer</storageType>
<measurementScale>
<ratio>
<unit>
<standardUnit>dimensionless</standardUnit>
</unit>
<numericDomain>
<numberType>real</numberType>

</numericDomain>
</ratio>
</measurementScale>

</attribute>
</attributeList>
</dataTable>
<otherEntity id="157_1568_site_locations.csv">
<entityName>157_1568_site_locations.csv</entityName>
<entityDescription>This file contains basic information about the site, including location and plot size</entityDescription>
<physical>
<objectName>157_1568_site_locations.csv</objectName>
<dataFormat>
<externallyDefinedFormat>
<formatName>csv file</formatName>
</externallyDefinedFormat>
</dataFormat>
<distribution>
<online>
<url function="download">http://www.lter.uaf.edu/ascii/files/157_1568_site_locations.csv</url>
</online>
</distribution>
</physical>
<entityType>csv file</entityType>
</otherEntity>
</dataset>
</ns0:eml>